ecomet_i2c_sensors/Platform.py
ecomet_i2c_sensors/__init__.py
ecomet_i2c_sensors/i2c.py
ecomet_i2c_sensors/i2c_command.py
ecomet_i2c_sensors/as3935/__init__.py
ecomet_i2c_sensors/as3935/as3935.py
ecomet_i2c_sensors/as3935/as3935_constant.py
ecomet_i2c_sensors/axp209/__init__.py
ecomet_i2c_sensors/axp209/axp209.py
ecomet_i2c_sensors/axp209/axp209_constant.py
ecomet_i2c_sensors/axp305/__init__.py
ecomet_i2c_sensors/axp305/axp305.py
ecomet_i2c_sensors/axp305/axp305_constant.py
ecomet_i2c_sensors/axp805/__init__.py
ecomet_i2c_sensors/axp805/axp805.py
ecomet_i2c_sensors/axp805/axp805_constant.py
ecomet_i2c_sensors/ecomet/ecomet01.py
ecomet_i2c_sensors/ecomet/ecomet01_constant.py
ecomet_i2c_sensors/eeprom/__init__.py
ecomet_i2c_sensors/eeprom/chip_list.py
ecomet_i2c_sensors/eeprom/eeprom_check.py
ecomet_i2c_sensors/eeprom/eeprom_read.py
ecomet_i2c_sensors/eeprom/eeprom_wipe.py
ecomet_i2c_sensors/eeprom/eeprom_write.py
ecomet_i2c_sensors/emc2301/__init__.py
ecomet_i2c_sensors/emc2301/emc2301.py
ecomet_i2c_sensors/emc2301/emc2301_constant.py
ecomet_i2c_sensors/emc2301/fan_type.py
ecomet_i2c_sensors/hdc1080/__init__.py
ecomet_i2c_sensors/hdc1080/hdc1080.py
ecomet_i2c_sensors/hdc1080/hdc1080_constant.py
ecomet_i2c_sensors/htu21/__init__.py
ecomet_i2c_sensors/htu21/htu21.py
ecomet_i2c_sensors/htu21/htu21_constant.py
ecomet_i2c_sensors/ina260/__init__.py
ecomet_i2c_sensors/ina260/ina260.py
ecomet_i2c_sensors/ina260/ina260_constant.py
ecomet_i2c_sensors/ina260/ina260_ui.py
ecomet_i2c_sensors/ina260/ina260_ui_constant.py
ecomet_i2c_sensors/isl2802x/__init__.py
ecomet_i2c_sensors/isl2802x/isl2802x.py
ecomet_i2c_sensors/isl2802x/isl2802x_constant.py
ecomet_i2c_sensors/isl2802x/isl2802x_ui.py
ecomet_i2c_sensors/isl2802x/isl2802x_ui_constant.py
ecomet_i2c_sensors/mcp3221/mcp3221.py
ecomet_i2c_sensors/mcp3221/mcp3221_constant.py
ecomet_i2c_sensors/ms5637/__init__.py
ecomet_i2c_sensors/ms5637/ms5637.py
ecomet_i2c_sensors/ms5637/ms5637_constant.py
ecomet_i2c_sensors/pca9557/__init__.py
ecomet_i2c_sensors-0.1.10.dist-info/licenses/LICENSE
ecomet_i2c_sensors-0.1.10.dist-info/METADATA
ecomet_i2c_sensors-0.1.10.dist-info/WHEEL
ecomet_i2c_sensors-0.1.10.dist-info/entry_points.txt
ecomet_i2c_sensors-0.1.10.dist-info/top_level.txt
ecomet_i2c_sensors-0.1.10.dist-info/RECORD
