Metadata-Version: 2.4
Name: ecomet-i2c-sensors
Version: 0.1.10
Summary: A short description of my package
Author-email: Marian Minar <mminar7@gmail.com>
License-Expression: GPL-3.0-only WITH Classpath-exception-2.0 OR BSD-3-Clause
Project-URL: Homepage, https://github.com/mamin27/ecomet_i2c_raspberry_tools
Project-URL: Repository, https://github.com/mamin27/ecomet_i2c_raspberry_tools
Keywords: raspberry,orangepi,allwinner,I2C,ecomet
Classifier: Development Status :: 5 - Production/Stable
Classifier: Intended Audience :: Developers
Classifier: Operating System :: POSIX :: Linux
Classifier: Programming Language :: Python :: 3
Requires-Python: >=3.11.2
License-File: LICENSE
Requires-Dist: Adafruit_PureIO>=1.1.8
Requires-Dist: numpy>=2.1.3
Requires-Dist: smbus2>=0.5.0
Requires-Dist: pyyaml>=6.0.2
Requires-Dist: pillow>=11.0.0
Requires-Dist: pypng>=0.20220715.0
Requires-Dist: qrcode>=8.0
Requires-Dist: typing-extensions>=4.12.2
Requires-Dist: crc>=7.0.0
Dynamic: license-file
